{
    "version": "https://jsonfeed.org/version/1",
    "title": "X_T • All posts by \"istp\" tag",
    "description": "人生如逆旅，我亦是行人",
    "home_page_url": "https://n1h1l157.github.io",
    "items": [
        {
            "id": "https://n1h1l157.github.io/2020/04/01/MBTI/ISTP%E8%A7%A3%E8%AF%BB/",
            "url": "https://n1h1l157.github.io/2020/04/01/MBTI/ISTP%E8%A7%A3%E8%AF%BB/",
            "title": "ISTP解读",
            "date_published": "2020-03-31T16:00:00.000Z",
            "content_html": "<p>坦率、诚实、讲求实效，他们平等、公正，喜欢行动而非漫谈。他们很谦逊，平和而寡言，往往显得冷酷而清高，而且容易害羞。</p>\n<h2 id=\"性格特征\"><a class=\"markdownIt-Anchor\" href=\"#性格特征\">#</a> 性格特征</h2>\n<p>通常精于使用工具和进行手工劳动，是使用工具的超级能手，他们具有使人赞叹不已绝妙技巧，他们胆大心细，喜欢不断尝试新事物，挑战自己。</p>\n<p>用 “水深静流”、“惜言如金” 可以很好地描述他们的特性。他们很难被人们读懂，也不喜欢抛头露面。</p>\n<p>“艺高人胆大”，同其他 SP 一样，ISTP 也喜欢冒险，寻求刺激，但他们不喜欢太张扬，许多 ISTP 默默无闻地尝试着很吓人的事情。</p>\n<p>在语言表达方面就弱一点，与他们精湛的技艺相比，ISTP 不喜欢长篇大论地说话。他们绝大多数时候都专注于自己眼前做的事情并且享受其中。</p>\n<p>向往无拘无束、自由自在的生活，在做某些决定的时候不太照顾到周围人的感受；由于过于专注于行动本身，容易沉浸在使用工具的过程中。</p>\n<p>认为行动比计划来得有效，为实现目标做些实实在在的工作才是正事。</p>\n<p>管理风格是突兀的、直接的、不合常规的。认为应该用 “尽管去做，不用说” 的方式去激励他人。</p>\n<p>会花很长时间学习和钻研自己感兴趣的东西，也需要一些时间来理清日常生活中复杂的头绪。热爱自由，厌恶被压迫被剥削。特别需要个人空间。</p>\n<p>有很强的观察能力和分析能力 (毕竟是很擅长做侦探和警察的人格)，所以能快速的分析一个人的喜好，分析一个人的弱点和痛点。</p>\n<p>istp 解决问题的方法倾向于先大量的观察分析，分析问题的结症所在然后用最高效的方法简单粗暴的解决问题。</p>\n<p>手艺人也是有短板的，因为只会注重当下 + 懒得关注外界，所以会目光不长远，三心二意容易放弃。又因为对外界各种事物都有兴趣，注意力分散，学东西容易博而不专。</p>\n<p>部分 istp 特别固执，对于自己认定的事特别执着，一定要做到，付出一切代价也要做到。不喜欢太平淡的生活，因为总要面对乱七八糟的人际关系，生活太平淡 istp 也会比较懒散不爱动脑。</p>\n<p>istp 有一个功能是 mbti16 大人格之首：身体的控制功能。</p>\n",
            "tags": [
                "ISTP"
            ]
        }
    ]
}